[
  {
    "School": "School of Management",
    "Department": "NA",
    "Program Name": "BACHELOR OF BUSINESS ADMINISTRATION",
    "Specialization": "GOM",
    "Section": "B",
    "Semester": 5,
    "Student Roll Number": "2K23MCUN04001",
    "Student Name": "AMAN KUMAR",
    "Mobile Number": 9650459509,
    "EmailID": "amansurya1512@gmail.com"
  },
  {
    "School": "School of Management",
    "Department": "NA",
    "Program Name": "BACHELOR OF BUSINESS ADMINISTRATION",
    "Specialization": "GOM",
    "Section": "B",
    "Semester": 5,
    "Student Roll Number": "2K23MCUN04002",
    "Student Name": "ANIRUDH SINGH",
    "Mobile Number": 9811841152,
    "EmailID": "raghuda1008@hotmail.com"
  },
  {
    "School": "School of Management",
    "Department": "NA",
    "Program Name": "BACHELOR OF BUSINESS ADMINISTRATION",
    "Specialization": "GOM",
    "Section": "B",
    "Semester": 5,
    "Student Roll Number": "2K23MCUN04003",
    "Student Name": "DHRUV PANCHAL",
    "Mobile Number": 9350472456,
    "EmailID": "jai76041@gmail.com"
  },
  {
    "School": "School of Management",
    "Department": "NA",
    "Program Name": "BACHELOR OF BUSINESS ADMINISTRATION",
    "Specialization": "GOM",
    "Section": "B",
    "Semester": 5,
    "Student Roll Number": "2K23MCUN04004",
    "Student Name": "HARSH THAKUR",
    "Mobile Number": 9711556884,
    "EmailID": "harshthakur5424@gmail.com"
  },
  {
    "School": "School of Management",
    "Department": "NA",
    "Program Name": "BACHELOR OF BUSINESS ADMINISTRATION",
    "Specialization": "GOM",
    "Section": "B",
    "Semester": 5,
    "Student Roll Number": "2K23MCUN04005",
    "Student Name": "JASKEERAT SINGH",
    "Mobile Number": 8588882404,
    "EmailID": "jaskeerat1812@gmail.com"
  },
  {
    "School": "School of Management",
    "Department": "NA",
    "Program Name": "BACHELOR OF BUSINESS ADMINISTRATION",
    "Specialization": "GOM",
    "Section": "B",
    "Semester": 5,
    "Student Roll Number": "2K23MCUN04006",
    "Student Name": "JOASH SAM MATHEW",
    "Mobile Number": 7303425923,
    "EmailID": "joashmathew45@gmail.com"
  },
  {
    "School": "School of Management",
    "Department": "NA",
    "Program Name": "BACHELOR OF BUSINESS ADMINISTRATION",
    "Specialization": "GOM",
    "Section": "B",
    "Semester": 5,
    "Student Roll Number": "2K23MCUN04007",
    "Student Name": "KARTIK GARG",
    "Mobile Number": 9319704504,
    "EmailID": "gargkartik424@gmail.com"
  },
  {
    "School": "School of Management",
    "Department": "NA",
    "Program Name": "BACHELOR OF BUSINESS ADMINISTRATION",
    "Specialization": "GOM",
    "Section": "B",
    "Semester": 5,
    "Student Roll Number": "2K23MCUN04008",
    "Student Name": "MAHAM REHMAN",
    "Mobile Number": 9871010910,
    "EmailID": "maham.rehman.2005@gmail.com"
  },
  {
    "School": "School of Management",
    "Department": "NA",
    "Program Name": "BACHELOR OF BUSINESS ADMINISTRATION",
    "Specialization": "GOM",
    "Section": "B",
    "Semester": 5,
    "Student Roll Number": "2K23MCUN04009",
    "Student Name": "SAQIB ALAM",
    "Mobile Number": 7827437927,
    "EmailID": "alamsaqib202@gmail.com"
  },
  {
    "School": "School of Management",
    "Department": "NA",
    "Program Name": "BACHELOR OF BUSINESS ADMINISTRATION",
    "Specialization": "GOM",
    "Section": "B",
    "Semester": 5,
    "Student Roll Number": "2K23MCUN04010",
    "Student Name": "SHIVAM",
    "Mobile Number": 9599120615,
    "EmailID": "talanshivam316@gmail.com"
  },
  {
    "School": "School of Management",
    "Department": "NA",
    "Program Name": "BACHELOR OF BUSINESS ADMINISTRATION",
    "Specialization": "GOM",
    "Section": "B",
    "Semester": 5,
    "Student Roll Number": "2K23MCUN04011",
    "Student Name": "SHUBHI SINGH",
    "Mobile Number": 8700311669,
    "EmailID": "shubhi200singh4@gmail.com"
  },
  {
    "School": "School of Management",
    "Department": "NA",
    "Program Name": "BACHELOR OF BUSINESS ADMINISTRATION",
    "Specialization": "GOM",
    "Section": "B",
    "Semester": 5,
    "Student Roll Number": "2K23MCUN04012",
    "Student Name": "SIMRAN JHA",
    "Mobile Number": 9811407412,
    "EmailID": "suniljha305@gmail.com"
  },
  {
    "School": "School of Management",
    "Department": "NA",
    "Program Name": "BACHELOR OF BUSINESS ADMINISTRATION",
    "Specialization": "GOM",
    "Section": "B",
    "Semester": 5,
    "Student Roll Number": "2K23MCUN04013",
    "Student Name": "TUSHAR DHAWAN",
    "Mobile Number": 9990456993,
    "EmailID": "tushar.dhawan01234567@gmail.com"
  },
  {
    "School": "School of Management",
    "Department": "NA",
    "Program Name": "BACHELOR OF BUSINESS ADMINISTRATION",
    "Specialization": "GOM",
    "Section": "B",
    "Semester": 5,
    "Student Roll Number": "2K23MCUN04014",
    "Student Name": "VANI KAUSHAL",
    "Mobile Number": 9311055730,
    "EmailID": "vanikaushal0206@gmail.com"
  },
  {
    "School": "School of Management",
    "Department": "NA",
    "Program Name": "BACHELOR OF BUSINESS ADMINISTRATION",
    "Specialization": "GOM",
    "Section": "B",
    "Semester": 5,
    "Student Roll Number": "2K23MCUN04015",
    "Student Name": "VIKAS",
    "Mobile Number": 9717177875,
    "EmailID": "laksmansingh82@gmail.com"
  },
  {
    "School": "School of Management",
    "Department": "NA",
    "Program Name": "BACHELOR OF BUSINESS ADMINISTRATION",
    "Specialization": "GOM",
    "Section": "B",
    "Semester": 5,
    "Student Roll Number": "2K23MCUN04016",
    "Student Name": "VIVEK SINGH",
    "Mobile Number": 8882710780,
    "EmailID": "issajaa8001@gmail.com"
  },
  {
    "School": "School of Management",
    "Department": "NA",
    "Program Name": "BACHELOR OF BUSINESS ADMINISTRATION",
    "Specialization": "GOM",
    "Section": "B",
    "Semester": 5,
    "Student Roll Number": "2K23MCUN04017",
    "Student Name": "ANUGRAH BISHT",
    "Mobile Number": 8929542541,
    "EmailID": "anugrahb758@gmail.com"
  },
  {
    "School": "School of Management",
    "Department": "NA",
    "Program Name": "BACHELOR OF BUSINESS ADMINISTRATION",
    "Specialization": "GHCM",
    "Section": "A",
    "Semester": 5,
    "Student Roll Number": "2K23MCUN03001",
    "Student Name": "DISHA DAS",
    "Mobile Number": 9560729579,
    "EmailID": "disha_das23@manavrachna.net"
  },
  {
    "School": "School of Management",
    "Department": "NA",
    "Program Name": "BACHELOR OF BUSINESS ADMINISTRATION",
    "Specialization": "GHCM",
    "Section": "A",
    "Semester": 5,
    "Student Roll Number": "2K23MCUN03003",
    "Student Name": "PALAK SOM",
    "Mobile Number": 7011739880,
    "EmailID": "palak_som23@manavrachna.net"
  },
  {
    "School": "School of Management",
    "Department": "NA",
    "Program Name": "BACHELOR OF BUSINESS ADMINISTRATION",
    "Specialization": "GHCM",
    "Section": "A",
    "Semester": 5,
    "Student Roll Number": "2K23MCUN03006",
    "Student Name": "YOGESH",
    "Mobile Number": 9053837135,
    "EmailID": "yogesh1_23@manavrachna.net"
  },
  {
    "School": "School of Management",
    "Department": "NA",
    "Program Name": "BACHELOR OF BUSINESS ADMINISTRATION",
    "Specialization": "FAA",
    "Section": "A",
    "Semester": 5,
    "Student Roll Number": "2K23MCUN02001",
    "Student Name": "AARTI KOHLI",
    "Mobile Number": 9310083589,
    "EmailID": "aartikohli900@gmail.com"
  },
  {
    "School": "School of Management",
    "Department": "NA",
    "Program Name": "BACHELOR OF BUSINESS ADMINISTRATION",
    "Specialization": "FAA",
    "Section": "A",
    "Semester": 5,
    "Student Roll Number": "2K23MCUN02002",
    "Student Name": "AMAN KUMAR",
    "Mobile Number": 7027892976,
    "EmailID": "amanchaudhary14321@gmail.com"
  },
  {
    "School": "School of Management",
    "Department": "NA",
    "Program Name": "BACHELOR OF BUSINESS ADMINISTRATION",
    "Specialization": "FAA",
    "Section": "A",
    "Semester": 5,
    "Student Roll Number": "2K23MCUN02003",
    "Student Name": "ANISHA SINGLA",
    "Mobile Number": 9319476150,
    "EmailID": "anishasingla2020@gmail.com"
  },
  {
    "School": "School of Management",
    "Department": "NA",
    "Program Name": "BACHELOR OF BUSINESS ADMINISTRATION",
    "Specialization": "FAA",
    "Section": "A",
    "Semester": 5,
    "Student Roll Number": "2K23MCUN02004",
    "Student Name": "ANSH BISHT",
    "Mobile Number": 8800506009,
    "EmailID": "anshbisht2005@gmail.com"
  },
  {
    "School": "School of Management",
    "Department": "NA",
    "Program Name": "BACHELOR OF BUSINESS ADMINISTRATION",
    "Specialization": "FAA",
    "Section": "A",
    "Semester": 5,
    "Student Roll Number": "2K23MCUN02005",
    "Student Name": "ARYAN FAUJDAR",
    "Mobile Number": 8595582426,
    "EmailID": "aryanfaujdar9999@gmail.com"
  },
  {
    "School": "School of Management",
    "Department": "NA",
    "Program Name": "BACHELOR OF BUSINESS ADMINISTRATION",
    "Specialization": "FAA",
    "Section": "A",
    "Semester": 5,
    "Student Roll Number": "2K23MCUN02007",
    "Student Name": "CHAITANYA GROVER",
    "Mobile Number": 9319642942,
    "EmailID": "groverlavish07@gmail.com"
  },
  {
    "School": "School of Management",
    "Department": "NA",
    "Program Name": "BACHELOR OF BUSINESS ADMINISTRATION",
    "Specialization": "FAA",
    "Section": "A",
    "Semester": 5,
    "Student Roll Number": "2K23MCUN02008",
    "Student Name": "DEVANSH ARORA",
    "Mobile Number": 9910107120,
    "EmailID": "devansharora0507@gmail.com"
  },
  {
    "School": "School of Management",
    "Department": "NA",
    "Program Name": "BACHELOR OF BUSINESS ADMINISTRATION",
    "Specialization": "FAA",
    "Section": "A",
    "Semester": 5,
    "Student Roll Number": "2K23MCUN02009",
    "Student Name": "GURNEEL SINGH NARANG",
    "Mobile Number": 8882141410,
    "EmailID": "gurneel08@gmail.com"
  },
  {
    "School": "School of Management",
    "Department": "NA",
    "Program Name": "BACHELOR OF BUSINESS ADMINISTRATION",
    "Specialization": "FAA",
    "Section": "A",
    "Semester": 5,
    "Student Roll Number": "2K23MCUN02010",
    "Student Name": "HARSHA SINGH",
    "Mobile Number": 9310988690,
    "EmailID": "HARSHASINGH1401@GMAIL.COM"
  },
  {
    "School": "School of Management",
    "Department": "NA",
    "Program Name": "BACHELOR OF BUSINESS ADMINISTRATION",
    "Specialization": "FAA",
    "Section": "A",
    "Semester": 5,
    "Student Roll Number": "2K23MCUN02011",
    "Student Name": "HARSHIT",
    "Mobile Number": 9817262627,
    "EmailID": "royalgarg903@gmail.com"
  },
  {
    "School": "School of Management",
    "Department": "NA",
    "Program Name": "BACHELOR OF BUSINESS ADMINISTRATION",
    "Specialization": "FAA",
    "Section": "A",
    "Semester": 5,
    "Student Roll Number": "2K23MCUN02012",
    "Student Name": "JIGYANSHU GARG",
    "Mobile Number": 9555631462,
    "EmailID": "jigyanshugarg2004@gmail.com"
  },
  {
    "School": "School of Management",
    "Department": "NA",
    "Program Name": "BACHELOR OF BUSINESS ADMINISTRATION",
    "Specialization": "FAA",
    "Section": "A",
    "Semester": 5,
    "Student Roll Number": "2K23MCUN02014",
    "Student Name": "KHUSHI",
    "Mobile Number": 9891914247,
    "EmailID": "khushidangi0036@gmail.com"
  },
  {
    "School": "School of Management",
    "Department": "NA",
    "Program Name": "BACHELOR OF BUSINESS ADMINISTRATION",
    "Specialization": "FAA",
    "Section": "A",
    "Semester": 5,
    "Student Roll Number": "2K23MCUN02015",
    "Student Name": "KUNAL GANDHI",
    "Mobile Number": 9810835715,
    "EmailID": "kunalgandhi147@gmail.com"
  },
  {
    "School": "School of Management",
    "Department": "NA",
    "Program Name": "BACHELOR OF BUSINESS ADMINISTRATION",
    "Specialization": "FAA",
    "Section": "A",
    "Semester": 5,
    "Student Roll Number": "2K23MCUN02016",
    "Student Name": "KUNAL GARG",
    "Mobile Number": 9810835715,
    "EmailID": "kunalgarg2712@gmail.com"
  },
  {
    "School": "School of Management",
    "Department": "NA",
    "Program Name": "BACHELOR OF BUSINESS ADMINISTRATION",
    "Specialization": "FAA",
    "Section": "A",
    "Semester": 5,
    "Student Roll Number": "2K23MCUN02017",
    "Student Name": "LAVISH GOENKA",
    "Mobile Number": 7027350366,
    "EmailID": "lovishgoenka31@gmail.com"
  },
  {
    "School": "School of Management",
    "Department": "NA",
    "Program Name": "BACHELOR OF BUSINESS ADMINISTRATION",
    "Specialization": "FAA",
    "Section": "A",
    "Semester": 5,
    "Student Roll Number": "2K23MCUN02018",
    "Student Name": "LOMI S YEPTHOMI",
    "Mobile Number": 8414888409,
    "EmailID": "lomiyepthomi10@gmail.com"
  },
  {
    "School": "School of Management",
    "Department": "NA",
    "Program Name": "BACHELOR OF BUSINESS ADMINISTRATION",
    "Specialization": "FAA",
    "Section": "A",
    "Semester": 5,
    "Student Roll Number": "2K23MCUN02020",
    "Student Name": "OJASAV MANGLA",
    "Mobile Number": 7496008399,
    "EmailID": "ojasavmangla6@gmail.com"
  },
  {
    "School": "School of Management",
    "Department": "NA",
    "Program Name": "BACHELOR OF BUSINESS ADMINISTRATION",
    "Specialization": "FAA",
    "Section": "A",
    "Semester": 5,
    "Student Roll Number": "2K23MCUN02021",
    "Student Name": "PRAYANSHU DESWAL",
    "Mobile Number": 8307242992,
    "EmailID": "deshwalprince4141@gmail.com"
  },
  {
    "School": "School of Management",
    "Department": "NA",
    "Program Name": "BACHELOR OF BUSINESS ADMINISTRATION",
    "Specialization": "FAA",
    "Section": "A",
    "Semester": 5,
    "Student Roll Number": "2K23MCUN02022",
    "Student Name": "PRECIOUS ARORA",
    "Mobile Number": 9560036497,
    "EmailID": "precious.arora2502@gmail.com"
  },
  {
    "School": "School of Management",
    "Department": "NA",
    "Program Name": "BACHELOR OF BUSINESS ADMINISTRATION",
    "Specialization": "FAA",
    "Section": "A",
    "Semester": 5,
    "Student Roll Number": "2K23MCUN02023",
    "Student Name": "RINKI",
    "Mobile Number": 9810307321,
    "EmailID": "rinkisingh8700@gmail.com"
  },
  {
    "School": "School of Management",
    "Department": "NA",
    "Program Name": "BACHELOR OF BUSINESS ADMINISTRATION",
    "Specialization": "FAA",
    "Section": "A",
    "Semester": 5,
    "Student Roll Number": "2K23MCUN02024",
    "Student Name": "RISHI GUSAIN",
    "Mobile Number": 9821057870,
    "EmailID": "rishigusain2005@gmail.com"
  },
  {
    "School": "School of Management",
    "Department": "NA",
    "Program Name": "BACHELOR OF BUSINESS ADMINISTRATION",
    "Specialization": "FAA",
    "Section": "A",
    "Semester": 5,
    "Student Roll Number": "2K23MCUN02025",
    "Student Name": "RITIKA SINGH",
    "Mobile Number": 7703898851,
    "EmailID": "RI8TIKASINGH@GMAIL.COM"
  },
  {
    "School": "School of Management",
    "Department": "NA",
    "Program Name": "BACHELOR OF BUSINESS ADMINISTRATION",
    "Specialization": "FAA",
    "Section": "A",
    "Semester": 5,
    "Student Roll Number": "2K23MCUN02026",
    "Student Name": "RIYA SINGH",
    "Mobile Number": 9873285592,
    "EmailID": "riyamavi137@gmail.com"
  },
  {
    "School": "School of Management",
    "Department": "NA",
    "Program Name": "BACHELOR OF BUSINESS ADMINISTRATION",
    "Specialization": "FAA",
    "Section": "A",
    "Semester": 5,
    "Student Roll Number": "2K23MCUN02029",
    "Student Name": "SAHIL KHAN",
    "Mobile Number": 9711254842,
    "EmailID": "sahil0001alvi@gmail.com"
  },
  {
    "School": "School of Management",
    "Department": "NA",
    "Program Name": "BACHELOR OF BUSINESS ADMINISTRATION",
    "Specialization": "FAA",
    "Section": "A",
    "Semester": 5,
    "Student Roll Number": "2K23MCUN02030",
    "Student Name": "SHIVAM RAGHAV",
    "Mobile Number": 7550500400,
    "EmailID": "shivamraghav005@gmail.com"
  },
  {
    "School": "School of Management",
    "Department": "NA",
    "Program Name": "BACHELOR OF BUSINESS ADMINISTRATION",
    "Specialization": "FAA",
    "Section": "A",
    "Semester": 5,
    "Student Roll Number": "2K23MCUN02031",
    "Student Name": "SRI PURUSHOTTAM NIKHIL RAO",
    "Mobile Number": 9031548301,
    "EmailID": "spnikhil9899@gmail.com"
  },
  {
    "School": "School of Management",
    "Department": "NA",
    "Program Name": "BACHELOR OF BUSINESS ADMINISTRATION",
    "Specialization": "FAA",
    "Section": "A",
    "Semester": 5,
    "Student Roll Number": "2K23MCUN02032",
    "Student Name": "TANISHQ KATHURIA",
    "Mobile Number": 9667837742,
    "EmailID": "kathuriatanishq02@gmail.com"
  },
  {
    "School": "School of Management",
    "Department": "NA",
    "Program Name": "BACHELOR OF BUSINESS ADMINISTRATION",
    "Specialization": "FAA",
    "Section": "A",
    "Semester": 5,
    "Student Roll Number": "2K23MCUN02033",
    "Student Name": "UZMA",
    "Mobile Number": 8368877802,
    "EmailID": "uzma0185@gmail.com"
  },
  {
    "School": "School of Management",
    "Department": "NA",
    "Program Name": "BACHELOR OF BUSINESS ADMINISTRATION",
    "Specialization": "FAA",
    "Section": "A",
    "Semester": 5,
    "Student Roll Number": "2K23MCUN02035",
    "Student Name": "VISHESH JAIN",
    "Mobile Number": 7011198111,
    "EmailID": "visheshjain1119@gmail.com"
  },
  {
    "School": "School of Management",
    "Department": "NA",
    "Program Name": "BACHELOR OF BUSINESS ADMINISTRATION",
    "Specialization": "FAA",
    "Section": "A",
    "Semester": 5,
    "Student Roll Number": "2K23MCUN02036",
    "Student Name": "YASH GARG",
    "Mobile Number": 9310149362,
    "EmailID": "gargyash1404.14@gmail.com"
  },
  {
    "School": "School of Management",
    "Department": "NA",
    "Program Name": "BACHELOR OF BUSINESS ADMINISTRATION",
    "Specialization": "FAA",
    "Section": "A",
    "Semester": 5,
    "Student Roll Number": "2K23MCUN02037",
    "Student Name": "YASH RAJPUT",
    "Mobile Number": 8178334484,
    "EmailID": "ryash8813@gmail.com"
  },
  {
    "School": "School of Management",
    "Department": "NA",
    "Program Name": "BACHELOR OF BUSINESS ADMINISTRATION",
    "Specialization": "FAA",
    "Section": "A",
    "Semester": 5,
    "Student Roll Number": "2K23MCUN02038",
    "Student Name": "YOGITA JINDAL",
    "Mobile Number": 9990764652,
    "EmailID": "jindalyogita9@gmail.com"
  },
  {
    "School": "School of Management",
    "Department": "NA",
    "Program Name": "BACHELOR OF BUSINESS ADMINISTRATION",
    "Specialization": "FAA",
    "Section": "A",
    "Semester": 5,
    "Student Roll Number": "2K24MCUM02001",
    "Student Name": "Somanshu Chaudhury",
    "Mobile Number": 8479999333,
    "EmailID": "somanshu12@gmail.com"
  },
  {
    "School": "School of Management",
    "Department": "NA",
    "Program Name": "BACHELOR OF BUSINESS ADMINISTRATION",
    "Specialization": "EFB",
    "Section": "B",
    "Semester": 5,
    "Student Roll Number": "2K23MCUN01001",
    "Student Name": "ADVITYA KUMAR SARIN",
    "Mobile Number": 9871533022,
    "EmailID": "geeta.isite@gmail.com"
  },
  {
    "School": "School of Management",
    "Department": "NA",
    "Program Name": "BACHELOR OF BUSINESS ADMINISTRATION",
    "Specialization": "EFB",
    "Section": "B",
    "Semester": 5,
    "Student Roll Number": "2K23MCUN01002",
    "Student Name": "AMRITPAL SINGH",
    "Mobile Number": 9625656076,
    "EmailID": "amritpalsinghbhamra001@gmail.com"
  },
  {
    "School": "School of Management",
    "Department": "NA",
    "Program Name": "BACHELOR OF BUSINESS ADMINISTRATION",
    "Specialization": "EFB",
    "Section": "B",
    "Semester": 5,
    "Student Roll Number": "2K23MCUN01003",
    "Student Name": "ARMAAN WADHWA",
    "Mobile Number": 7678572582,
    "EmailID": "armaanwadhwa05@gmail.com"
  },
  {
    "School": "School of Management",
    "Department": "NA",
    "Program Name": "BACHELOR OF BUSINESS ADMINISTRATION",
    "Specialization": "EFB",
    "Section": "B",
    "Semester": 5,
    "Student Roll Number": "2K23MCUN01004",
    "Student Name": "BHAVYA GUPTA",
    "Mobile Number": 9560830403,
    "EmailID": "bhavyagupta9654@gmail.com"
  },
  {
    "School": "School of Management",
    "Department": "NA",
    "Program Name": "BACHELOR OF BUSINESS ADMINISTRATION",
    "Specialization": "EFB",
    "Section": "B",
    "Semester": 5,
    "Student Roll Number": "2K23MCUN01005",
    "Student Name": "DEV RAJ KASANA",
    "Mobile Number": 9999039796,
    "EmailID": "devkasana36@gmail.com"
  },
  {
    "School": "School of Management",
    "Department": "NA",
    "Program Name": "BACHELOR OF BUSINESS ADMINISTRATION",
    "Specialization": "EFB",
    "Section": "B",
    "Semester": 5,
    "Student Roll Number": "2K23MCUN01006",
    "Student Name": "DUSHYANT GOYAL",
    "Mobile Number": 7206792648,
    "EmailID": "dushyantg055@gmail.com"
  },
  {
    "School": "School of Management",
    "Department": "NA",
    "Program Name": "BACHELOR OF BUSINESS ADMINISTRATION",
    "Specialization": "EFB",
    "Section": "B",
    "Semester": 5,
    "Student Roll Number": "2K23MCUN01007",
    "Student Name": "ISHAAN NARANG",
    "Mobile Number": 8368143218,
    "EmailID": "ishaanpearl@gmail.com"
  },
  {
    "School": "School of Management",
    "Department": "NA",
    "Program Name": "BACHELOR OF BUSINESS ADMINISTRATION",
    "Specialization": "EFB",
    "Section": "B",
    "Semester": 5,
    "Student Roll Number": "2K23MCUN01008",
    "Student Name": "JAYANT MIGLANI",
    "Mobile Number": 9311589053,
    "EmailID": "jayantmiglani098@gmail.com"
  },
  {
    "School": "School of Management",
    "Department": "NA",
    "Program Name": "BACHELOR OF BUSINESS ADMINISTRATION",
    "Specialization": "EFB",
    "Section": "B",
    "Semester": 5,
    "Student Roll Number": "2K23MCUN01009",
    "Student Name": "KHUSHI DHANKHARD",
    "Mobile Number": 9871690006,
    "EmailID": "khushidhankhard@gmail.com"
  },
  {
    "School": "School of Management",
    "Department": "NA",
    "Program Name": "BACHELOR OF BUSINESS ADMINISTRATION",
    "Specialization": "EFB",
    "Section": "B",
    "Semester": 5,
    "Student Roll Number": "2K23MCUN01010",
    "Student Name": "KUBER SAINI",
    "Mobile Number": 9971822406,
    "EmailID": "kubersaini1105@gmail.com"
  },
  {
    "School": "School of Management",
    "Department": "NA",
    "Program Name": "BACHELOR OF BUSINESS ADMINISTRATION",
    "Specialization": "EFB",
    "Section": "B",
    "Semester": 5,
    "Student Roll Number": "2K23MCUN01011",
    "Student Name": "KUNAL THAKRAN",
    "Mobile Number": 7011115693,
    "EmailID": "kunalthakran2001@gmail.com"
  },
  {
    "School": "School of Management",
    "Department": "NA",
    "Program Name": "BACHELOR OF BUSINESS ADMINISTRATION",
    "Specialization": "EFB",
    "Section": "B",
    "Semester": 5,
    "Student Roll Number": "2K23MCUN01012",
    "Student Name": "MAHIMA GANDHI",
    "Mobile Number": 9643803111,
    "EmailID": "mahimaaa1703@gmail.com"
  },
  {
    "School": "School of Management",
    "Department": "NA",
    "Program Name": "BACHELOR OF BUSINESS ADMINISTRATION",
    "Specialization": "EFB",
    "Section": "B",
    "Semester": 5,
    "Student Roll Number": "2K23MCUN01013",
    "Student Name": "MANAN MENDIRATTA",
    "Mobile Number": 9711907140,
    "EmailID": "manan1923m@gmail.com"
  },
  {
    "School": "School of Management",
    "Department": "NA",
    "Program Name": "BACHELOR OF BUSINESS ADMINISTRATION",
    "Specialization": "EFB",
    "Section": "B",
    "Semester": 5,
    "Student Roll Number": "2K23MCUN01014",
    "Student Name": "MANAS SAHNI",
    "Mobile Number": 8851421374,
    "EmailID": "manassahni22@gmail.com"
  },
  {
    "School": "School of Management",
    "Department": "NA",
    "Program Name": "BACHELOR OF BUSINESS ADMINISTRATION",
    "Specialization": "EFB",
    "Section": "B",
    "Semester": 5,
    "Student Roll Number": "2K23MCUN01015",
    "Student Name": "MANAV NAIN",
    "Mobile Number": 9540648000,
    "EmailID": "manavnain7@gmail.com"
  },
  {
    "School": "School of Management",
    "Department": "NA",
    "Program Name": "BACHELOR OF BUSINESS ADMINISTRATION",
    "Specialization": "EFB",
    "Section": "B",
    "Semester": 5,
    "Student Roll Number": "2K23MCUN01016",
    "Student Name": "MAYANK YADAV",
    "Mobile Number": 9289070493,
    "EmailID": "mayankyadavkumar25@gmail.com"
  },
  {
    "School": "School of Management",
    "Department": "NA",
    "Program Name": "BACHELOR OF BUSINESS ADMINISTRATION",
    "Specialization": "EFB",
    "Section": "B",
    "Semester": 5,
    "Student Roll Number": "2K23MCUN01017",
    "Student Name": "MUKUL SINGLA",
    "Mobile Number": 9992181555,
    "EmailID": "mukulsingla11012004@gmail.com"
  },
  {
    "School": "School of Management",
    "Department": "NA",
    "Program Name": "BACHELOR OF BUSINESS ADMINISTRATION",
    "Specialization": "EFB",
    "Section": "B",
    "Semester": 5,
    "Student Roll Number": "2K23MCUN01018",
    "Student Name": "MUKUND GULATI",
    "Mobile Number": 9958767116,
    "EmailID": "mukundgulati16@gmail.com"
  },
  {
    "School": "School of Management",
    "Department": "NA",
    "Program Name": "BACHELOR OF BUSINESS ADMINISTRATION",
    "Specialization": "EFB",
    "Section": "B",
    "Semester": 5,
    "Student Roll Number": "2K23MCUN01019",
    "Student Name": "NABH HARITASH",
    "Mobile Number": 8601170001,
    "EmailID": "nabhsharma0007@gmail.com"
  },
  {
    "School": "School of Management",
    "Department": "NA",
    "Program Name": "BACHELOR OF BUSINESS ADMINISTRATION",
    "Specialization": "EFB",
    "Section": "B",
    "Semester": 5,
    "Student Roll Number": "2K23MCUN01020",
    "Student Name": "NILESH KUMAR",
    "Mobile Number": 7260817819,
    "EmailID": "nileshkumar19035@gmail.com"
  },
  {
    "School": "School of Management",
    "Department": "NA",
    "Program Name": "BACHELOR OF BUSINESS ADMINISTRATION",
    "Specialization": "EFB",
    "Section": "B",
    "Semester": 5,
    "Student Roll Number": "2K23MCUN01021",
    "Student Name": "NITISH",
    "Mobile Number": 7027666600,
    "EmailID": "gargnitish395@gmail.com"
  },
  {
    "School": "School of Management",
    "Department": "NA",
    "Program Name": "BACHELOR OF BUSINESS ADMINISTRATION",
    "Specialization": "EFB",
    "Section": "B",
    "Semester": 5,
    "Student Roll Number": "2K23MCUN01022",
    "Student Name": "OM ANUJ PREYASKAR",
    "Mobile Number": 8757651645,
    "EmailID": "asukumar425@gmail.com"
  },
  {
    "School": "School of Management",
    "Department": "NA",
    "Program Name": "BACHELOR OF BUSINESS ADMINISTRATION",
    "Specialization": "EFB",
    "Section": "B",
    "Semester": 5,
    "Student Roll Number": "2K23MCUN01023",
    "Student Name": "PRABHNEET SINGH",
    "Mobile Number": 8826440481,
    "EmailID": "sale.expertsolutions@gmail.com"
  },
  {
    "School": "School of Management",
    "Department": "NA",
    "Program Name": "BACHELOR OF BUSINESS ADMINISTRATION",
    "Specialization": "EFB",
    "Section": "B",
    "Semester": 5,
    "Student Roll Number": "2K23MCUN01024",
    "Student Name": "PRIYANSHI SINGH",
    "Mobile Number": 7080341829,
    "EmailID": "priyanshisingh06082005@gmail.com"
  },
  {
    "School": "School of Management",
    "Department": "NA",
    "Program Name": "BACHELOR OF BUSINESS ADMINISTRATION",
    "Specialization": "EFB",
    "Section": "B",
    "Semester": 5,
    "Student Roll Number": "2K23MCUN01025",
    "Student Name": "PUSHKAR KANSAL",
    "Mobile Number": 9810347833,
    "EmailID": "pushkar16kansal@gmail.com"
  },
  {
    "School": "School of Management",
    "Department": "NA",
    "Program Name": "BACHELOR OF BUSINESS ADMINISTRATION",
    "Specialization": "EFB",
    "Section": "B",
    "Semester": 5,
    "Student Roll Number": "2K23MCUN01026",
    "Student Name": "RAGHAV AGGARWAL",
    "Mobile Number": 9999425293,
    "EmailID": "abdvk91@gmail.com"
  },
  {
    "School": "School of Management",
    "Department": "NA",
    "Program Name": "BACHELOR OF BUSINESS ADMINISTRATION",
    "Specialization": "EFB",
    "Section": "B",
    "Semester": 5,
    "Student Roll Number": "2K23MCUN01027",
    "Student Name": "REHAAN",
    "Mobile Number": 8368844137,
    "EmailID": "rehaanalvi123@gmail.com"
  },
  {
    "School": "School of Management",
    "Department": "NA",
    "Program Name": "BACHELOR OF BUSINESS ADMINISTRATION",
    "Specialization": "EFB",
    "Section": "B",
    "Semester": 5,
    "Student Roll Number": "2K23MCUN01028",
    "Student Name": "ROHIT",
    "Mobile Number": 7982509311,
    "EmailID": "garima9200@gmail.com"
  },
  {
    "School": "School of Management",
    "Department": "NA",
    "Program Name": "BACHELOR OF BUSINESS ADMINISTRATION",
    "Specialization": "EFB",
    "Section": "B",
    "Semester": 5,
    "Student Roll Number": "2K23MCUN01029",
    "Student Name": "ROUNAK JHA",
    "Mobile Number": 9650310078,
    "EmailID": "shankarnjha@yahoo.co.in"
  },
  {
    "School": "School of Management",
    "Department": "NA",
    "Program Name": "BACHELOR OF BUSINESS ADMINISTRATION",
    "Specialization": "EFB",
    "Section": "B",
    "Semester": 5,
    "Student Roll Number": "2K23MCUN01030",
    "Student Name": "SARAL",
    "Mobile Number": 8168018805,
    "EmailID": "saralraheja2005@gmail.com"
  },
  {
    "School": "School of Management",
    "Department": "NA",
    "Program Name": "BACHELOR OF BUSINESS ADMINISTRATION",
    "Specialization": "EFB",
    "Section": "B",
    "Semester": 5,
    "Student Roll Number": "2K23MCUN01031",
    "Student Name": "SHIV KUMAR",
    "Mobile Number": 8287974916,
    "EmailID": "surajnaagar14@gmail.com"
  },
  {
    "School": "School of Management",
    "Department": "NA",
    "Program Name": "BACHELOR OF BUSINESS ADMINISTRATION",
    "Specialization": "EFB",
    "Section": "B",
    "Semester": 5,
    "Student Roll Number": "2K23MCUN01032",
    "Student Name": "SIDDHARTH KASANA",
    "Mobile Number": 9718902459,
    "EmailID": "oveer0561@gmail.com"
  },
  {
    "School": "School of Management",
    "Department": "NA",
    "Program Name": "BACHELOR OF BUSINESS ADMINISTRATION",
    "Specialization": "EFB",
    "Section": "B",
    "Semester": 5,
    "Student Roll Number": "2K23MCUN01033",
    "Student Name": "TUSHAR MAHATO",
    "Mobile Number": 6295961116,
    "EmailID": "tusharmahato48@gmail.com"
  },
  {
    "School": "School of Management",
    "Department": "NA",
    "Program Name": "BACHELOR OF BUSINESS ADMINISTRATION",
    "Specialization": "EFB",
    "Section": "B",
    "Semester": 5,
    "Student Roll Number": "2K23MCUN01034",
    "Student Name": "VAIBHAV K BHARDWAJ",
    "Mobile Number": 6359979963,
    "EmailID": "vaibhavkbhardwaj555@gmail.com"
  },
  {
    "School": "School of Management",
    "Department": "NA",
    "Program Name": "BACHELOR OF BUSINESS ADMINISTRATION",
    "Specialization": "EFB",
    "Section": "B",
    "Semester": 5,
    "Student Roll Number": "2K23MCUN01035",
    "Student Name": "VANSH TANWAR",
    "Mobile Number": 8700724846,
    "EmailID": "vanshtanwar.47@gmail.com"
  },
  {
    "School": "School of Management",
    "Department": "NA",
    "Program Name": "BACHELOR OF BUSINESS ADMINISTRATION",
    "Specialization": "EFB",
    "Section": "B",
    "Semester": 5,
    "Student Roll Number": "2K23MCUN01036",
    "Student Name": "VEDANG BAJPAI",
    "Mobile Number": 7217716082,
    "EmailID": "vedangbajapi05@gmail.com"
  },
  {
    "School": "School of Management",
    "Department": "NA",
    "Program Name": "BACHELOR OF BUSINESS ADMINISTRATION",
    "Specialization": "EFB",
    "Section": "B",
    "Semester": 5,
    "Student Roll Number": "2K23MCUN01037",
    "Student Name": "YASH SINGH",
    "Mobile Number": 8375857575,
    "EmailID": "yashsingh167099@gmail.com"
  },
  {
    "School": "School of Management",
    "Department": "NA",
    "Program Name": "BACHELOR OF BUSINESS ADMINISTRATION",
    "Specialization": "BA",
    "Section": "C",
    "Semester": 5,
    "Student Roll Number": "2K23MCUN05001",
    "Student Name": "ABHAY MOURYA",
    "Mobile Number": 9891617230,
    "EmailID": "abhaymaurya012@gmail.com"
  },
  {
    "School": "School of Management",
    "Department": "NA",
    "Program Name": "BACHELOR OF BUSINESS ADMINISTRATION",
    "Specialization": "BA",
    "Section": "C",
    "Semester": 5,
    "Student Roll Number": "2K23MCUN05002",
    "Student Name": "ABHIYANK KAUSHIK",
    "Mobile Number": 8595755886,
    "EmailID": "abhiyankkaushik953@gmail.com"
  },
  {
    "School": "School of Management",
    "Department": "NA",
    "Program Name": "BACHELOR OF BUSINESS ADMINISTRATION",
    "Specialization": "BA",
    "Section": "C",
    "Semester": 5,
    "Student Roll Number": "2K23MCUN05003",
    "Student Name": "AMAN GUPTA",
    "Mobile Number": 9868047236,
    "EmailID": "gupta1608aman@gmail.com"
  },
  {
    "School": "School of Management",
    "Department": "NA",
    "Program Name": "BACHELOR OF BUSINESS ADMINISTRATION",
    "Specialization": "BA",
    "Section": "C",
    "Semester": 5,
    "Student Roll Number": "2K23MCUN05004",
    "Student Name": "AMODIT VERMA",
    "Mobile Number": 9560068197,
    "EmailID": "vermaamoditmv@gmail.com"
  },
  {
    "School": "School of Management",
    "Department": "NA",
    "Program Name": "BACHELOR OF BUSINESS ADMINISTRATION",
    "Specialization": "BA",
    "Section": "C",
    "Semester": 5,
    "Student Roll Number": "2K23MCUN05005",
    "Student Name": "ARYAN KHATRI",
    "Mobile Number": 9958700474,
    "EmailID": "aryankhatri2626@gmail.com"
  },
  {
    "School": "School of Management",
    "Department": "NA",
    "Program Name": "BACHELOR OF BUSINESS ADMINISTRATION",
    "Specialization": "BA",
    "Section": "C",
    "Semester": 5,
    "Student Roll Number": "2K23MCUN05006",
    "Student Name": "ASHISH",
    "Mobile Number": 9650108965,
    "EmailID": "ashishyadavsec85@gmail.com"
  },
  {
    "School": "School of Management",
    "Department": "NA",
    "Program Name": "BACHELOR OF BUSINESS ADMINISTRATION",
    "Specialization": "BA",
    "Section": "C",
    "Semester": 5,
    "Student Roll Number": "2K23MCUN05007",
    "Student Name": "AYUSH",
    "Mobile Number": 9821444418,
    "EmailID": "ayushmadan031@gmail.com"
  },
  {
    "School": "School of Management",
    "Department": "NA",
    "Program Name": "BACHELOR OF BUSINESS ADMINISTRATION",
    "Specialization": "BA",
    "Section": "C",
    "Semester": 5,
    "Student Roll Number": "2K23MCUN05008",
    "Student Name": "BAIBHAV CHAKRABORTY",
    "Mobile Number": 9873620588,
    "EmailID": "nag.subarna@gmail.com"
  },
  {
    "School": "School of Management",
    "Department": "NA",
    "Program Name": "BACHELOR OF BUSINESS ADMINISTRATION",
    "Specialization": "BA",
    "Section": "C",
    "Semester": 5,
    "Student Roll Number": "2K23MCUN05009",
    "Student Name": "DEEPAK",
    "Mobile Number": 8810324913,
    "EmailID": "deepakphagna6177@gmail.com"
  },
  {
    "School": "School of Management",
    "Department": "NA",
    "Program Name": "BACHELOR OF BUSINESS ADMINISTRATION",
    "Specialization": "BA",
    "Section": "C",
    "Semester": 5,
    "Student Roll Number": "2K23MCUN05010",
    "Student Name": "HAMMAD ANSARI",
    "Mobile Number": 9654124224,
    "EmailID": "ihdesham12@hotmail.com"
  },
  {
    "School": "School of Management",
    "Department": "NA",
    "Program Name": "BACHELOR OF BUSINESS ADMINISTRATION",
    "Specialization": "BA",
    "Section": "C",
    "Semester": 5,
    "Student Roll Number": "2K23MCUN05011",
    "Student Name": "HARSH KAUSHIK",
    "Mobile Number": 9971739533,
    "EmailID": "hkaushik610@gmail.com"
  },
  {
    "School": "School of Management",
    "Department": "NA",
    "Program Name": "BACHELOR OF BUSINESS ADMINISTRATION",
    "Specialization": "BA",
    "Section": "C",
    "Semester": 5,
    "Student Roll Number": "2K23MCUN05012",
    "Student Name": "HARSHIT GARG",
    "Mobile Number": 9729565878,
    "EmailID": "piyushgarg5638@gmail.com"
  },
  {
    "School": "School of Management",
    "Department": "NA",
    "Program Name": "BACHELOR OF BUSINESS ADMINISTRATION",
    "Specialization": "BA",
    "Section": "C",
    "Semester": 5,
    "Student Roll Number": "2K23MCUN05013",
    "Student Name": "KOMAL SRIVASTAVA",
    "Mobile Number": 9310769965,
    "EmailID": "komalsrivastava2005@gmail.com"
  },
  {
    "School": "School of Management",
    "Department": "NA",
    "Program Name": "BACHELOR OF BUSINESS ADMINISTRATION",
    "Specialization": "BA",
    "Section": "C",
    "Semester": 5,
    "Student Roll Number": "2K23MCUN05014",
    "Student Name": "KRISHNA AHUJA",
    "Mobile Number": 8368118806,
    "EmailID": "ahujadinesh1974@gmail.com"
  },
  {
    "School": "School of Management",
    "Department": "NA",
    "Program Name": "BACHELOR OF BUSINESS ADMINISTRATION",
    "Specialization": "BA",
    "Section": "C",
    "Semester": 5,
    "Student Roll Number": "2K23MCUN05015",
    "Student Name": "KUSHAGRA VERMA",
    "Mobile Number": 6307412225,
    "EmailID": "kushagrav814@gmail.com"
  },
  {
    "School": "School of Management",
    "Department": "NA",
    "Program Name": "BACHELOR OF BUSINESS ADMINISTRATION",
    "Specialization": "BA",
    "Section": "C",
    "Semester": 5,
    "Student Roll Number": "2K23MCUN05016",
    "Student Name": "MANISH KUMAR",
    "Mobile Number": 9354322975,
    "EmailID": "manishmukeriya2003.mm@gamil.com"
  },
  {
    "School": "School of Management",
    "Department": "NA",
    "Program Name": "BACHELOR OF BUSINESS ADMINISTRATION",
    "Specialization": "BA",
    "Section": "C",
    "Semester": 5,
    "Student Roll Number": "2K23MCUN05017",
    "Student Name": "MOHD ARSHAN ZOHAIB",
    "Mobile Number": 9871696391,
    "EmailID": "hfurqan460@gmail.com"
  },
  {
    "School": "School of Management",
    "Department": "NA",
    "Program Name": "BACHELOR OF BUSINESS ADMINISTRATION",
    "Specialization": "BA",
    "Section": "C",
    "Semester": 5,
    "Student Roll Number": "2K23MCUN05018",
    "Student Name": "PARTH BHATIA",
    "Mobile Number": 9250485340,
    "EmailID": "parthbhatia5708@gmail.com"
  },
  {
    "School": "School of Management",
    "Department": "NA",
    "Program Name": "BACHELOR OF BUSINESS ADMINISTRATION",
    "Specialization": "BA",
    "Section": "C",
    "Semester": 5,
    "Student Roll Number": "2K23MCUN05019",
    "Student Name": "PARTH CHOPRA",
    "Mobile Number": 7042620823,
    "EmailID": "rekha3481.rc@gmail.com"
  },
  {
    "School": "School of Management",
    "Department": "NA",
    "Program Name": "BACHELOR OF BUSINESS ADMINISTRATION",
    "Specialization": "BA",
    "Section": "C",
    "Semester": 5,
    "Student Roll Number": "2K23MCUN05020",
    "Student Name": "PRANAV MUTREJA",
    "Mobile Number": 9899816368,
    "EmailID": "rajpranavmutreja06@gmail.com"
  },
  {
    "School": "School of Management",
    "Department": "NA",
    "Program Name": "BACHELOR OF BUSINESS ADMINISTRATION",
    "Specialization": "BA",
    "Section": "C",
    "Semester": 5,
    "Student Roll Number": "2K23MCUN05021",
    "Student Name": "PRANSHU BANSAL",
    "Mobile Number": 9205940280,
    "EmailID": "bansalpranshu2009@gmail.com"
  },
  {
    "School": "School of Management",
    "Department": "NA",
    "Program Name": "BACHELOR OF BUSINESS ADMINISTRATION",
    "Specialization": "BA",
    "Section": "C",
    "Semester": 5,
    "Student Roll Number": "2K23MCUN05022",
    "Student Name": "RAAYAT ABBAS RIZVI",
    "Mobile Number": 9999556786,
    "EmailID": "saqriz786@gmail.com"
  },
  {
    "School": "School of Management",
    "Department": "NA",
    "Program Name": "BACHELOR OF BUSINESS ADMINISTRATION",
    "Specialization": "BA",
    "Section": "C",
    "Semester": 5,
    "Student Roll Number": "2K23MCUN05023",
    "Student Name": "RAJAT SINGH",
    "Mobile Number": 9996834253,
    "EmailID": "tanwarrajat29@gmail.com"
  },
  {
    "School": "School of Management",
    "Department": "NA",
    "Program Name": "BACHELOR OF BUSINESS ADMINISTRATION",
    "Specialization": "BA",
    "Section": "C",
    "Semester": 5,
    "Student Roll Number": "2K23MCUN05024",
    "Student Name": "RAKSHAN ATTRI",
    "Mobile Number": 7303017526,
    "EmailID": "Rakshanattri29@gmail.com"
  },
  {
    "School": "School of Management",
    "Department": "NA",
    "Program Name": "BACHELOR OF BUSINESS ADMINISTRATION",
    "Specialization": "BA",
    "Section": "C",
    "Semester": 5,
    "Student Roll Number": "2K23MCUN05025",
    "Student Name": "RIDUL GAMBHIR",
    "Mobile Number": 8178121108,
    "EmailID": "ridul637@gmail.com"
  },
  {
    "School": "School of Management",
    "Department": "NA",
    "Program Name": "BACHELOR OF BUSINESS ADMINISTRATION",
    "Specialization": "BA",
    "Section": "C",
    "Semester": 5,
    "Student Roll Number": "2K23MCUN05026",
    "Student Name": "RUDRAKSH DHAR",
    "Mobile Number": 8595709315,
    "EmailID": "ashokdhar2@gmail.com"
  },
  {
    "School": "School of Management",
    "Department": "NA",
    "Program Name": "BACHELOR OF BUSINESS ADMINISTRATION",
    "Specialization": "BA",
    "Section": "C",
    "Semester": 5,
    "Student Roll Number": "2K23MCUN05027",
    "Student Name": "SARTAJ NAGPAL",
    "Mobile Number": 7428550709,
    "EmailID": "sartaj.nagpal08@gmail.com"
  },
  {
    "School": "School of Management",
    "Department": "NA",
    "Program Name": "BACHELOR OF BUSINESS ADMINISTRATION",
    "Specialization": "BA",
    "Section": "C",
    "Semester": 5,
    "Student Roll Number": "2K23MCUN05028",
    "Student Name": "SAURAV CHANDILA",
    "Mobile Number": 9999950829,
    "EmailID": "sauravchandila3137@gmail.com"
  },
  {
    "School": "School of Management",
    "Department": "NA",
    "Program Name": "BACHELOR OF BUSINESS ADMINISTRATION",
    "Specialization": "BA",
    "Section": "C",
    "Semester": 5,
    "Student Roll Number": "2K23MCUN05029",
    "Student Name": "SHREYA KATYAYAN",
    "Mobile Number": 9315061079,
    "EmailID": "shreyakatyayan7@gmail.com"
  },
  {
    "School": "School of Management",
    "Department": "NA",
    "Program Name": "BACHELOR OF BUSINESS ADMINISTRATION",
    "Specialization": "BA",
    "Section": "C",
    "Semester": 5,
    "Student Roll Number": "2K23MCUN05030",
    "Student Name": "SUJAY BANIK",
    "Mobile Number": 8588079939,
    "EmailID": "apexrishib@gmail.com"
  },
  {
    "School": "School of Management",
    "Department": "NA",
    "Program Name": "BACHELOR OF BUSINESS ADMINISTRATION",
    "Specialization": "BA",
    "Section": "C",
    "Semester": 5,
    "Student Roll Number": "2K23MCUN05031",
    "Student Name": "SUKHMANPREET SINGH",
    "Mobile Number": 8929675979,
    "EmailID": "ssukhmanpreet179@gmail.com"
  },
  {
    "School": "School of Management",
    "Department": "NA",
    "Program Name": "BACHELOR OF BUSINESS ADMINISTRATION",
    "Specialization": "BA",
    "Section": "C",
    "Semester": 5,
    "Student Roll Number": "2K23MCUN05032",
    "Student Name": "VAIBHAV SHARMA",
    "Mobile Number": 8505861414,
    "EmailID": "jpsharma11962@gmail.com"
  }
]